verified/__init__.py
verified/foo.py
verified-0.0.0.dist-info/LICENSE
verified-0.0.0.dist-info/METADATA
verified-0.0.0.dist-info/WHEEL
verified-0.0.0.dist-info/RECORD
